.DS_Store
helloworld_Bernd.py
helloworld_Bernd-0.0.1.dist-info/METADATA
helloworld_Bernd-0.0.1.dist-info/WHEEL
helloworld_Bernd-0.0.1.dist-info/top_level.txt
helloworld_Bernd-0.0.1.dist-info/RECORD
